{
  "url": "https://sunnystep.com/products/dream-mesh-ballerina",
  "name": "Dream Mesh Ballerina",
  "brand": "Sunnystep",
  "sku": "8886484534871",
  "price": "145",
  "priceCurrency": "SGD",
  "availability": "https://schema.org/InStock",
  "description": "Dream Mesh Ballerina-Sunnystep walking shoes are designed to minimize stress to the feet and the body. The shoes come with structured insoles and are designed for long walking and standing.",
  "images": [
    "images/products/07_dream-mesh-ballerina_1.png",
    "images/products/07_dream-mesh-ballerina_2.jpg"
  ],
  "sourceImageUrls": [
    "https://img.myshopline.com/image/store/1679305542267/5-63.png?w&#x3D;1024&amp;h&#x3D;1024",
    "https://img.myshopline.com/image/store/1679305542267/ST08-136.jpg?w&#x3D;3000&amp;h&#x3D;3000"
  ]
}